ProSad/An_Wb.py
ProSad/How.py
ProSad/Socket.py
ProSad/__init__.py
ProSad/client.py
ProSad/encryption.py
ProSad-2.0.4.dist-info/LICENCE
ProSad-2.0.4.dist-info/METADATA
ProSad-2.0.4.dist-info/WHEEL
ProSad-2.0.4.dist-info/top_level.txt
ProSad-2.0.4.dist-info/RECORD
