Metadata-Version: 2.1
Name: ProSad
Version: 2.0.4
Summary: Rubika Library Bot
Home-page: https://github.com/pypa/sampleproject
Author: mamadcoder
Author-email: x.coder.2721@gmail.com
License: MIT
Keywords: rubika,bot,robot,library,rubikalib,rubikalib.ml,rubikalib.ir,ProSad,prosad,libraryProSad,Rubika,Python
Classifier: Development Status :: 3 - Alpha
Classifier: Intended Audience :: Developers
Classifier: Topic :: Software Development :: Build Tools
Classifier: License :: OSI Approved :: MIT License
Classifier: Programming Language :: Python :: Implementation :: PyPy
Classifier: Programming Language :: Python :: 3
Classifier: Programming Language :: Python :: 3.4
Classifier: Programming Language :: Python :: 3.5
Classifier: Programming Language :: Python :: 3.6
Classifier: Programming Language :: Python :: 3.7
Classifier: Programming Language :: Python :: 3.8
Classifier: Programming Language :: Python :: 3.9
License-File: LICENCE
